django_string_renderer-0.5.0.dist-info/licenses/LICENSE
stringrenderer/__init__.py
stringrenderer/locale/fr/LC_MESSAGES/django.mo
tests/__init__.py
tests/test_settings.py
tests/tests.py
django_string_renderer-0.5.0.dist-info/METADATA
django_string_renderer-0.5.0.dist-info/WHEEL
django_string_renderer-0.5.0.dist-info/top_level.txt
django_string_renderer-0.5.0.dist-info/RECORD
