Metadata-Version: 2.4
Name: django-string-renderer
Version: 0.5.0
Summary: A thin wrapper around the Django templating system to render any string as a template. It provides an easy way to render any user inputted string as a regular django template.
Home-page: https://github.com/dprog-philippe-docourt/django-string-renderer
Author: Philippe Docourt
Author-email: contact@dprog.net
License: MIT
Keywords: templating django
Classifier: Programming Language :: Python :: 3.10
Classifier: Programming Language :: Python :: 3.11
Classifier: Programming Language :: Python :: 3.12
Classifier: Programming Language :: Python :: 3.13
Classifier: License :: OSI Approved :: MIT License
Classifier: Operating System :: OS Independent
Classifier: Framework :: Django
Classifier: Framework :: Django :: 4.2
Classifier: Framework :: Django :: 5.2
Classifier: Development Status :: 5 - Production/Stable
Classifier: Natural Language :: English
Requires-Python: >=3.10
License-File: LICENSE
Requires-Dist: django
Requires-Dist: djangocodemirror
Dynamic: author
Dynamic: author-email
Dynamic: classifier
Dynamic: description
Dynamic: description-content-type
Dynamic: home-page
Dynamic: keywords
Dynamic: license
Dynamic: license-file
Dynamic: requires-dist
Dynamic: requires-python
Dynamic: summary
